bookkeep/__init__.py
bookkeep/my_units_defs.txt
bookkeep/read_only_book.py
bookkeep/smart_book.py
bookkeep/unit_manager.py
bookkeep/unit_registry.py
bookkeep/utils.py
bookkeep-0.1.dist-info/METADATA
bookkeep-0.1.dist-info/WHEEL
bookkeep-0.1.dist-info/top_level.txt
bookkeep-0.1.dist-info/RECORD
