Metadata-Version: 2.1
Name: bookkeep
Version: 0.1
Summary: bookeep keeps track of units, bounds, and immutable items.
Home-page: https://github.com/yoelcortes/Bookkeeping
Author: Yoel Cortes-Pena
Author-email: yoelcortes@gmail.com
License: MIT
Download-URL: https://github.com/yoelcortes/Bookkeeping.git
Platform: Windows
Requires-Dist: numpy
Requires-Dist: pandas
Requires-Dist: pint
Requires-Dist: IPython
Requires-Dist: colorama
